<annotation verified="no"><folder>images</folder><filename>ac83702f3</filename><path>/home/badhon/Documents/thesis/final_dataset/inrae/images/ac83702f3.jpg</path><source><database>Unknown</database></source><size><width>1024</width><height>1024</height><depth>3</depth></size><segmented>0</segmented><object><type>robndbox</type><name>wheat_head</name><pose>Unspecified</pose><truncated>0</truncated><difficult>0</difficult><robndbox><cx>927.6191</cx><cy>427.6521</cy><w>72.5229</w><h>71.2022</h><angle>0.259317</angle></robndbox></object><object><type>robndbox</type><name>wheat_head</name><pose>Unspecified</pose><truncated>0</truncated><difficult>0</difficult><robndbox><cx>204.995</cx><cy>144.0293</cy><w>96.9782</w><h>68.4224</h><angle>2.737422</angle></robndbox></object><object><type>robndbox</type><name>wheat_head</name><pose>Unspecified</pose><truncated>0</truncated><difficult>0</difficult><robndbox><cx>905.2415</cx><cy>667.356</cy><w>80.6089</w><h>61.3033</h><angle>1.587697</angle></robndbox></object><object><type>robndbox</type><name>wheat_head</name><pose>Unspecified</pose><truncated>0</truncated><difficult>0</difficult><robndbox><cx>264.6873</cx><cy>708.8651</cy><w>84.6426</w><h>76.2875</h><angle>1.948597</angle></robndbox></object><object><type>robndbox</type><name>wheat_head</name><pose>Unspecified</pose><truncated>0</truncated><difficult>0</difficult><robndbox><cx>320.9634</cx><cy>263.7362</cy><w>86.6399</w><h>58.9716</h><angle>1.586101</angle></robndbox></object><object><type>robndbox</type><name>wheat_head</name><pose>Unspecified</pose><truncated>0</truncated><difficult>0</difficult><robndbox><cx>133.2422</cx><cy>680.3381</cy><w>160.1194</w><h>69.9949</h><angle>2.580282</angle></robndbox></object><object><type>robndbox</type><name>wheat_head</name><pose>Unspecified</pose><truncated>0</truncated><difficult>0</difficult><robndbox><cx>287.1012</cx><cy>469.2325</cy><w>83.9227</w><h>53.6679</h><angle>0.966522</angle></robndbox></object><object><type>robndbox</type><name>wheat_head</name><pose>Unspecified</pose><truncated>0</truncated><difficult>0</difficult><robndbox><cx>547.1782</cx><cy>133.7002</cy><w>90.013</w><h>67.978</h><angle>1.565635</angle></robndbox></object><object><type>robndbox</type><name>wheat_head</name><pose>Unspecified</pose><truncated>0</truncated><difficult>0</difficult><robndbox><cx>704.9426</cx><cy>428.3424</cy><w>88.6837</w><h>54.6911</h><angle>1.033798</angle></robndbox></object><object><type>robndbox</type><name>wheat_head</name><pose>Unspecified</pose><truncated>0</truncated><difficult>0</difficult><robndbox><cx>922.6714</cx><cy>888.7358</cy><w>124.0188</w><h>53.2542</h><angle>1.119659</angle></robndbox></object><object><type>robndbox</type><name>wheat_head</name><pose>Unspecified</pose><truncated>0</truncated><difficult>0</difficult><robndbox><cx>783.2516</cx><cy>540.1423</cy><w>62.3639</w><h>51.8767</h><angle>1.195677</angle></robndbox></object><object><type>robndbox</type><name>wheat_head</name><pose>Unspecified</pose><truncated>0</truncated><difficult>0</difficult><robndbox><cx>718.0364</cx><cy>176.2769</cy><w>132.0648</w><h>52.4936</h><angle>1.503952</angle></robndbox></object><object><type>robndbox</type><name>wheat_head</name><pose>Unspecified</pose><truncated>0</truncated><difficult>0</difficult><robndbox><cx>545.2187</cx><cy>692.0613</cy><w>76.5958</w><h>64.8487</h><angle>1.698241</angle></robndbox></object><object><type>robndbox</type><name>wheat_head</name><pose>Unspecified</pose><truncated>0</truncated><difficult>0</difficult><robndbox><cx>775.1821</cx><cy>18.3406</cy><w>77.2097</w><h>46.9868</h><angle>0.081509</angle></robndbox></object><object><type>robndbox</type><name>wheat_head</name><pose>Unspecified</pose><truncated>0</truncated><difficult>0</difficult><robndbox><cx>557.7524</cx><cy>590.1432</cy><w>65.0812</w><h>40.4089</h><angle>1.861698</angle></robndbox></object><object><type>robndbox</type><name>wheat_head</name><pose>Unspecified</pose><truncated>0</truncated><difficult>0</difficult><robndbox><cx>521.3024</cx><cy>954.3693</cy><w>109.816</w><h>50.1137</h><angle>2.253172</angle></robndbox></object><object><type>robndbox</type><name>wheat_head</name><pose>Unspecified</pose><truncated>0</truncated><difficult>0</difficult><robndbox><cx>463.0466</cx><cy>217.7275</cy><w>88.9956</w><h>49.3941</h><angle>0.430452</angle></robndbox></object><object><type>robndbox</type><name>wheat_head</name><pose>Unspecified</pose><truncated>0</truncated><difficult>0</difficult><robndbox><cx>115.5089</cx><cy>446.6654</cy><w>47.0057</w><h>40.7681</h><angle>1.692651</angle></robndbox></object><object><type>robndbox</type><name>wheat_head</name><pose>Unspecified</pose><truncated>0</truncated><difficult>0</difficult><robndbox><cx>432.1769</cx><cy>469.3649</cy><w>92.2119</w><h>49.8332</h><angle>3.134592</angle></robndbox></object><object><type>robndbox</type><name>wheat_head</name><pose>Unspecified</pose><truncated>0</truncated><difficult>0</difficult><robndbox><cx>771.4386</cx><cy>782.066</cy><w>59.5496</w><h>48.8718</h><angle>0.968688</angle></robndbox></object><object><type>robndbox</type><name>wheat_head</name><pose>Unspecified</pose><truncated>0</truncated><difficult>0</difficult><robndbox><cx>45.4272</cx><cy>278.1472</cy><w>115.3238</w><h>74.8962</h><angle>1.749737</angle></robndbox></object><object><type>robndbox</type><name>wheat_head</name><pose>Unspecified</pose><truncated>0</truncated><difficult>0</difficult><robndbox><cx>812.0641</cx><cy>985.8902</cy><w>99.8248</w><h>71.4341</h><angle>0.735793</angle></robndbox></object><object><type>robndbox</type><name>wheat_head</name><pose>Unspecified</pose><truncated>0</truncated><difficult>0</difficult><robndbox><cx>840.1876</cx><cy>178.0033</cy><w>46.6905</w><h>45.9512</h><angle>0.815692</angle></robndbox></object><object><type>robndbox</type><name>wheat_head</name><pose>Unspecified</pose><truncated>0</truncated><difficult>0</difficult><robndbox><cx>802.4572</cx><cy>146.0389</cy><w>88.3629</w><h>68.1859</h><angle>1.661456</angle></robndbox></object></annotation>