<annotation verified="no"><folder>images</folder><filename>e1427550f</filename><path>/home/badhon/Documents/thesis/final_dataset/inrae/images/e1427550f.jpg</path><source><database>Unknown</database></source><size><width>1024</width><height>1024</height><depth>3</depth></size><segmented>0</segmented><object><type>robndbox</type><name>wheat_head</name><pose>Unspecified</pose><truncated>0</truncated><difficult>0</difficult><robndbox><cx>500.9165</cx><cy>303.0742</cy><w>96.5882</w><h>61.0794</h><angle>1.206008</angle></robndbox></object><object><type>robndbox</type><name>wheat_head</name><pose>Unspecified</pose><truncated>0</truncated><difficult>0</difficult><robndbox><cx>734.6396</cx><cy>678.3903</cy><w>220.6572</w><h>83.3922</h><angle>0.972038</angle></robndbox></object><object><type>robndbox</type><name>wheat_head</name><pose>Unspecified</pose><truncated>0</truncated><difficult>0</difficult><robndbox><cx>933.9161</cx><cy>838.2661</cy><w>109.2824</w><h>50.9785</h><angle>2.582055</angle></robndbox></object><object><type>robndbox</type><name>wheat_head</name><pose>Unspecified</pose><truncated>0</truncated><difficult>0</difficult><robndbox><cx>370.7134</cx><cy>786.4798</cy><w>89.2072</w><h>66.1448</h><angle>2.476624</angle></robndbox></object><object><type>robndbox</type><name>wheat_head</name><pose>Unspecified</pose><truncated>0</truncated><difficult>0</difficult><robndbox><cx>642.2067</cx><cy>109.9888</cy><w>265.4515</w><h>79.6682</h><angle>0.581439</angle></robndbox></object><object><type>robndbox</type><name>wheat_head</name><pose>Unspecified</pose><truncated>0</truncated><difficult>0</difficult><robndbox><cx>377.3119</cx><cy>414.248</cy><w>95.5507</w><h>50.8733</h><angle>2.25952</angle></robndbox></object><object><type>robndbox</type><name>wheat_head</name><pose>Unspecified</pose><truncated>0</truncated><difficult>0</difficult><robndbox><cx>471.3679</cx><cy>102.3504</cy><w>195.7353</w><h>57.1406</h><angle>1.849218</angle></robndbox></object><object><type>robndbox</type><name>wheat_head</name><pose>Unspecified</pose><truncated>0</truncated><difficult>0</difficult><robndbox><cx>269.3943</cx><cy>114.0916</cy><w>211.8759</w><h>81.7867</h><angle>1.140036</angle></robndbox></object><object><type>robndbox</type><name>wheat_head</name><pose>Unspecified</pose><truncated>0</truncated><difficult>0</difficult><robndbox><cx>981.7678</cx><cy>589.018</cy><w>132.5623</w><h>58.0899</h><angle>0.98498</angle></robndbox></object><object><type>robndbox</type><name>wheat_head</name><pose>Unspecified</pose><truncated>0</truncated><difficult>0</difficult><robndbox><cx>648.9496</cx><cy>392.073</cy><w>454.4882</w><h>73.1201</h><angle>1.590589</angle></robndbox></object><object><type>robndbox</type><name>wheat_head</name><pose>Unspecified</pose><truncated>0</truncated><difficult>0</difficult><robndbox><cx>106.194</cx><cy>381.6654</cy><w>298.7085</w><h>83.6118</h><angle>2.02486</angle></robndbox></object><object><type>robndbox</type><name>wheat_head</name><pose>Unspecified</pose><truncated>0</truncated><difficult>0</difficult><robndbox><cx>190.2535</cx><cy>468.4441</cy><w>314.2368</w><h>89.6189</h><angle>2.749598</angle></robndbox></object><object><type>robndbox</type><name>wheat_head</name><pose>Unspecified</pose><truncated>0</truncated><difficult>0</difficult><robndbox><cx>1001.9029</cx><cy>444.5688</cy><w>113.2571</w><h>44.1104</h><angle>1.39302</angle></robndbox></object><object><type>robndbox</type><name>wheat_head</name><pose>Unspecified</pose><truncated>0</truncated><difficult>0</difficult><robndbox><cx>56.6076</cx><cy>140.6507</cy><w>260.8233</w><h>80.6992</h><angle>1.981457</angle></robndbox></object><object><type>robndbox</type><name>wheat_head</name><pose>Unspecified</pose><truncated>0</truncated><difficult>0</difficult><robndbox><cx>620.5933</cx><cy>214.6729</cy><w>116.6396</w><h>60.0813</h><angle>2.682338</angle></robndbox></object><object><type>robndbox</type><name>wheat_head</name><pose>Unspecified</pose><truncated>0</truncated><difficult>0</difficult><robndbox><cx>349.5482</cx><cy>27.4815</cy><w>125.3877</w><h>64.4683</h><angle>0.235973</angle></robndbox></object><object><type>robndbox</type><name>wheat_head</name><pose>Unspecified</pose><truncated>0</truncated><difficult>0</difficult><robndbox><cx>74.014</cx><cy>658.6899</cy><w>49.3811</w><h>42.3218</h><angle>1.611865</angle></robndbox></object><object><type>robndbox</type><name>wheat_head</name><pose>Unspecified</pose><truncated>0</truncated><difficult>0</difficult><robndbox><cx>668.2753</cx><cy>249.5752</cy><w>167.6544</w><h>49.2628</h><angle>2.63633</angle></robndbox></object></annotation>